dinkycache/__init__.py
dinkycache/dinky.py
dinkycache-1.0.3.dist-info/METADATA
dinkycache-1.0.3.dist-info/WHEEL
dinkycache-1.0.3.dist-info/top_level.txt
dinkycache-1.0.3.dist-info/RECORD
